cmd_talk/__init__.py
cmd_talk/msg.py
cmd_talk/settings.py
cmd_talk/user.py
cmd_talk/utils.py
cmd_talk-0.1.dist-info/METADATA
cmd_talk-0.1.dist-info/WHEEL
cmd_talk-0.1.dist-info/entry_points.txt
cmd_talk-0.1.dist-info/top_level.txt
cmd_talk-0.1.dist-info/RECORD
