Metadata-Version: 2.1
Name: cmd-talk
Version: 0.1
Summary: Command talk component of Hybrid Cloud.
Home-page: https://github.com/newcoderlife/cmd-talk
Author: newcoderlife
Author-email: newcoderlife@outlook.com
License: MPL-2.0
Platform: UNKNOWN
